[
  {
    "id": "1",
    "name": "Anderson County Health Department",
    "website": "http://www.achealthdept.org/",
    "twitter": "",
    "facebook": "",
    "rss": "",
    "phone": "(865) 425-8820",
    "email": "t.miller@state.tn.us",
    "address": "710 N Main St Ste A\nClinton, TN 37716-3143"
  },
  {
    "id": "2",
    "name": "Bedford County Health Department",
    "website": "",
    "twitter": "",
    "facebook": "",
    "rss": "",
    "phone": "(931) 684-3426",
    "email": "gie.faulkner@tn.gov",
    "address": "140 Dover St\nShelbyville, TN 37160-2776"
  },
  {
    "id": "3",
    "name": "Benton County Health Department",
    "website": "",
    "twitter": "",
    "facebook": "",
    "rss": "",
    "phone": "(731) 584-4944",
    "email": "acy.Byrd@state.tn.us",
    "address": "225 Hospital Dr\nCamden, TN 38320-1619"
  },
  {
    "id": "4",
    "name": "Bledsoe County Health Department",
    "website": "",
    "twitter": "",
    "facebook": "",
    "rss": "",
    "phone": "(423) 447-2149",
    "email": "cki.carr@tn.gov",
    "address": "1185 Alvin York Hwy\nPikeville, TN 37367-4926"
  },
  {
    "id": "5",
    "name": "Blount County Health Department",
    "website": "http://www.blounttn.org/291/Health-Department",
    "twitter": "",
    "facebook": "",
    "rss": "",
    "phone": "(865) 983-4582",
    "email": "bert.schmidt@tn.gov",
    "address": "301 Mcghee ST\nMaryville, TN 37801-6811"
  },
  {
    "id": "6",
    "name": "Bradley County Health Department",
    "website": "",
    "twitter": "",
    "facebook": "",
    "rss": "",
    "phone": "(423) 728-7020 (105)",
    "email": "annie.bentley@tn.gov",
    "address": "201 Dooley St Se\nCleveland, TN 37311-6220"
  },
  {
    "id": "7",
    "name": "Campbell County Health Department",
    "website": "",
    "twitter": "",
    "facebook": "",
    "rss": "",
    "phone": "(423) 562-8351",
    "email": "arles.H.Turner@state.tn.us",
    "address": "162 Sharp-Perkins Road\nJacksboro, TN 37757"
  },
  {
    "id": "8",
    "name": "Cannon County Health Department",
    "website": "",
    "twitter": "",
    "facebook": "",
    "rss": "",
    "phone": "(615) 563-4243",
    "email": "chael.railling@state.tn.us",
    "address": "106 Alexander DR\nWoodbury, TN 37190-5275"
  },
  {
    "id": "9",
    "name": "Carroll County Health Department",
    "website": "",
    "twitter": "",
    "facebook": "",
    "rss": "",
    "phone": "(731) 986-1990",
    "email": "ily.Rushing@tn.gov",
    "address": "633 High ST\nHuntingdon, TN 38344-1703"
  },
  {
    "id": "10",
    "name": "Carter County Health Department",
    "website": "",
    "twitter": "",
    "facebook": "",
    "rss": "",
    "phone": "(423) 543-2521",
    "email": "roline.hurt@tn.gov",
    "address": "403 E G St\nElizabethton, TN 37643-3288"
  },
  {
    "id": "11",
    "name": "Chattanooga-Hamilton County Health Department",
    "website": "http://health.hamiltontn.org",
    "twitter": "",
    "facebook": "",
    "rss": "",
    "phone": "(423) 209-8000",
    "email": "ckyB@mail.HamiltonTN.gov",
    "address": "921 E 3Rd St\nChattanooga, TN 37403-2102"
  },
  {
    "id": "12",
    "name": "Cheatham County Health Department",
    "website": "",
    "twitter": "",
    "facebook": "",
    "rss": "",
    "phone": "(615) 792-4318",
    "email": "ittany.tate@tn.gov",
    "address": "162 County Services Rd Ste 200\nAshland City, TN 37015-1748"
  },
  {
    "id": "13",
    "name": "Chester County Health Department",
    "website": "",
    "twitter": "",
    "facebook": "",
    "rss": "",
    "phone": "(731) 989-7108",
    "email": "ttie.kiddy@tn.gov",
    "address": "PO BOX 323\nHenderson, TN 38340-0323"
  },
  {
    "id": "14",
    "name": "Claiborne County Health Department",
    "website": "",
    "twitter": "",
    "facebook": "",
    "rss": "",
    "phone": "(423) 626-4291",
    "email": "arles.H.Turner@state.tn.us",
    "address": "620 Davis Drive\nTazewell, TN 37879-0183"
  },
  {
    "id": "15",
    "name": "Clay County Health Department",
    "website": "",
    "twitter": "",
    "facebook": "",
    "rss": "",
    "phone": "(931) 243-2651",
    "email": "dy.langford@state.tn.us",
    "address": "115 Guffey St\nCelina, TN 38551-4089"
  },
  {
    "id": "16",
    "name": "Cocke County Health Department",
    "website": "http://www.cockecountytn.gov/county-officials/health-department/",
    "twitter": "",
    "facebook": "",
    "rss": "",
    "phone": "(423) 623-8733",
    "email": "na.Chambers@tn.gov",
    "address": "430 College St\nNewport, TN 37821-3752"
  },
  {
    "id": "17",
    "name": "Coffee County Health Department",
    "website": "https://www.coffeecountytn.gov/177/Health-Department",
    "twitter": "",
    "facebook": "",
    "rss": "",
    "phone": "(931) 723-5134",
    "email": "bbie.Dickey@tn.gov",
    "address": "800 Parks St\nManchester, TN 37355-2482"
  },
  {
    "id": "18",
    "name": "Crockett County Health Center",
    "website": "",
    "twitter": "",
    "facebook": "",
    "rss": "",
    "phone": "(731) 696-2505",
    "email": "rilyn.Barnes@state.tn.us",
    "address": "209 N Bells St\nAlamo, TN 38001-1755"
  },
  {
    "id": "19",
    "name": "Cumberland County Health Department",
    "website": "",
    "twitter": "",
    "facebook": "",
    "rss": "",
    "phone": "(931) 484-6196",
    "email": "ndy.doyle@tn.gov",
    "address": "1503 S Main ST\nCrossville, TN 38555-5967"
  },
  {
    "id": "20",
    "name": "Decatur County Health Department",
    "website": "",
    "twitter": "",
    "facebook": "",
    "rss": "",
    "phone": "(731) 852-2461",
    "email": "ttie.kiddy@tn.gov",
    "address": "PO BOX 178\nDecaturville, TN 38329-0178"
  },
  {
    "id": "21",
    "name": "Dekalb County Health Department",
    "website": "",
    "twitter": "",
    "facebook": "",
    "rss": "",
    "phone": "(615) 597-7599",
    "email": "chael.railling@tn.gov",
    "address": "254 Tiger Dr\nSmithville, TN 37166-6812"
  },
  {
    "id": "22",
    "name": "Dickson County Health Department",
    "website": "",
    "twitter": "",
    "facebook": "",
    "rss": "",
    "phone": "(615) 446-2839",
    "email": "errie.booker@tn.gov",
    "address": "301 W End Ave\nDickson, TN 37055-1725"
  },
  {
    "id": "23",
    "name": "Dyer County Health Department",
    "website": "",
    "twitter": "",
    "facebook": "",
    "rss": "",
    "phone": "(731) 285-7311",
    "email": "m.James@state.tn.us",
    "address": "1755 Parr Ave\nDyersburg, TN 38024-2004"
  },
  {
    "id": "24",
    "name": "East Region, Tennessee Department of Health",
    "website": "https://www.tn.gov/health/health-program-areas/oralhealth/clinics/east-tennessee-region.html",
    "twitter": "",
    "facebook": "",
    "rss": "",
    "phone": "(865) 549-5251",
    "email": "net.ridley@tn.gov",
    "address": "2101 Medical Center Way\nKnoxville, TN 37920-3257"
  },
  {
    "id": "25",
    "name": "Fayette County Health Department",
    "website": "http://tn.gov",
    "twitter": "",
    "facebook": "",
    "rss": "",
    "phone": "(901) 465-5243",
    "email": "ctoria.Price@tn.gov",
    "address": "PO BOX 188\nSomerville, TN 38068-0188"
  },
  {
    "id": "26",
    "name": "Fentress County Health Department",
    "website": "",
    "twitter": "",
    "facebook": "",
    "rss": "",
    "phone": "(931) 879-9936",
    "email": "dy.langford@tn.gov",
    "address": "240 Colonial Cir Ste A\nJamestown, TN 38556-3924"
  },
  {
    "id": "27",
    "name": "Franklin County Health Department",
    "website": "",
    "twitter": "",
    "facebook": "",
    "rss": "",
    "phone": "(931) 967-3826",
    "email": "arlene.nunley@tn.gov",
    "address": "338 Joyce Ln\nWinchester, TN 37398-3326"
  },
  {
    "id": "28",
    "name": "Gibson County Health Department",
    "website": "",
    "twitter": "",
    "facebook": "",
    "rss": "",
    "phone": "(731) 855-7601",
    "email": "nna.taylor@tn.gov",
    "address": "PO BOX 8\nTrenton, TN 38382-0008"
  },
  {
    "id": "29",
    "name": "Giles County Health Department",
    "website": "",
    "twitter": "",
    "facebook": "",
    "rss": "",
    "phone": "(931) 363-5506",
    "email": "net.mcalister@tn.gov",
    "address": "209 S Cedar Ln\nPulaski, TN 38478-3502"
  },
  {
    "id": "30",
    "name": "Grainger County Health Department",
    "website": "",
    "twitter": "",
    "facebook": "",
    "rss": "",
    "phone": "(865) 828-5247",
    "email": "il.harmon@tn.gov",
    "address": "PO BOX 27\nRutledge, TN 37861-0027"
  },
  {
    "id": "31",
    "name": "Greene County Health Department",
    "website": "",
    "twitter": "",
    "facebook": "",
    "rss": "",
    "phone": "(423) 798-1749",
    "email": "aun.street@tn.gov",
    "address": "PO BOX 159\nGreeneville, TN 37744-0159"
  },
  {
    "id": "32",
    "name": "Grundy County Health Department",
    "website": "http://www.grundycountytn.net/health_dept/index.html",
    "twitter": "",
    "facebook": "",
    "rss": "",
    "phone": "(931) 692-3641",
    "email": "arlene.nunley@tn.gov",
    "address": "PO BOX 65\nAltamont, TN 37301-0065"
  },
  {
    "id": "33",
    "name": "Hamblen County Health Department",
    "website": "",
    "twitter": "",
    "facebook": "",
    "rss": "",
    "phone": "(423) 318-1542",
    "email": "errie.Montgomery@tn.gov",
    "address": "331 W Main St\nMorristown, TN 37814-4621"
  },
  {
    "id": "34",
    "name": "Hancock County Health Department",
    "website": "",
    "twitter": "",
    "facebook": "",
    "rss": "",
    "phone": "(423) 733-2228",
    "email": "rnet.southerland@tn.gov",
    "address": "PO Box 267\nSneedville, TN 37869-0267"
  },
  {
    "id": "35",
    "name": "Hardeman County Health Department",
    "website": "",
    "twitter": "",
    "facebook": "",
    "rss": "",
    "phone": "(731) 658-5291",
    "email": "ren.codjoe@state.tn.us",
    "address": "PO Box 670\nBolivar, TN 38008-0670"
  },
  {
    "id": "36",
    "name": "Hardin County Health Department",
    "website": "",
    "twitter": "",
    "facebook": "",
    "rss": "",
    "phone": "(731) 925-2557",
    "email": "ttie.kiddy@tn.gov",
    "address": "PO BOX 397\nSavannah, TN 38372-0397"
  },
  {
    "id": "37",
    "name": "Hawkins County Health Department",
    "website": "https://www.hawkinscountytn.gov/",
    "twitter": "",
    "facebook": "",
    "rss": "",
    "phone": "(423) 272-7641",
    "email": "aun.Street@hawkinscountytn.gov",
    "address": "PO Box 488\nRogersville, TN 37857-0488"
  },
  {
    "id": "38",
    "name": "Hawkins County Health Department / Church Hill Office",
    "website": "",
    "twitter": "",
    "facebook": "",
    "rss": "",
    "phone": "(423) 357-5341",
    "email": "san.venable@state.tn.us",
    "address": "PO BOX 209\nChurch Hill, TN 37642-0209"
  },
  {
    "id": "39",
    "name": "Haywood County Health Department",
    "website": "",
    "twitter": "",
    "facebook": "",
    "rss": "",
    "phone": "(731) 772-0463",
    "email": "tt.mcdaniel@tn.gov",
    "address": "950 E Main St\nBrownsville, TN 38012-2647"
  },
  {
    "id": "40",
    "name": "Henderson County Health Department",
    "website": "",
    "twitter": "",
    "facebook": "",
    "rss": "",
    "phone": "(731) 968-8148",
    "email": "ily.Rushing@tn.gov",
    "address": "PO BOX 1050\nLexington, TN 38351-1050"
  },
  {
    "id": "41",
    "name": "Henry County Health Department",
    "website": "",
    "twitter": "",
    "facebook": "",
    "rss": "",
    "phone": "(731) 642-4025",
    "email": "acy.Byrd@tn.gov",
    "address": "803 Joy St\nParis, TN 38242-4529"
  },
  {
    "id": "42",
    "name": "Hickman County Health Department",
    "website": "",
    "twitter": "",
    "facebook": "",
    "rss": "",
    "phone": "(931) 729-3516",
    "email": "rah.russell@tn.gov",
    "address": "111 Murphree Ave\nCenterville, TN 37033-1418"
  },
  {
    "id": "43",
    "name": "Houston County Health Department",
    "website": "",
    "twitter": "",
    "facebook": "",
    "rss": "",
    "phone": "(931) 289-3463",
    "email": "ren.anderson@tn.gov",
    "address": "60 Court Sq\nErin, TN 37061-4166"
  },
  {
    "id": "44",
    "name": "Humphreys County Health Department",
    "website": "http://humphreystn.com/heathcare/index.html",
    "twitter": "",
    "facebook": "",
    "rss": "",
    "phone": "(931) 296-2231",
    "email": "errie.booker@tn.gov",
    "address": "725 Holly Ln\nWaverly, TN 37185-3284"
  },
  {
    "id": "45",
    "name": "Jackson - Madison County Health Department",
    "website": "http://www.jmchd.com",
    "twitter": "",
    "facebook": "",
    "rss": "",
    "phone": "(731) 423-3020",
    "email": "mtedford@madisoncountytn.gov",
    "address": "804 N Parkway\nJackson, TN 38305-3058"
  },
  {
    "id": "46",
    "name": "Jackson County Health Department",
    "website": "",
    "twitter": "",
    "facebook": "",
    "rss": "",
    "phone": "(931) 268-0218",
    "email": "sh.gipson@tn.gov",
    "address": "PO BOX 312\nGainesboro, TN 38562-0312"
  },
  {
    "id": "47",
    "name": "Jefferson County Health Department",
    "website": "",
    "twitter": "",
    "facebook": "",
    "rss": "",
    "phone": "(865) 397-3930",
    "email": "errie.Montgomery@tn.gov",
    "address": "PO Box 130\nDandridge, TN 37725-0130"
  },
  {
    "id": "48",
    "name": "Johnson County Health Department",
    "website": "",
    "twitter": "",
    "facebook": "",
    "rss": "",
    "phone": "(423) 357-5341",
    "email": "roline.hurt@state.tn.us",
    "address": "715 W Main St\nMountain City, TN 37683-1217"
  },
  {
    "id": "49",
    "name": "Knox County Health Department",
    "website": "http://www.knoxcounty.org/health",
    "twitter": "https://twitter.com/KnoxCoHealthTN",
    "facebook": "",
    "rss": "",
    "phone": "(865) 215-5000",
    "email": "alth@knoxcounty.org",
    "address": "140 Dameron Ave\nKnoxville, TN 37917-6413"
  },
  {
    "id": "50",
    "name": "Lake County Health Department",
    "website": "",
    "twitter": "",
    "facebook": "",
    "rss": "",
    "phone": "(731) 253-9954",
    "email": "m.James@tn.gov",
    "address": "400 Hwy. 78 S.\nTiptonville, TN 38079"
  },
  {
    "id": "51",
    "name": "Lauderdale County Health Department",
    "website": "",
    "twitter": "",
    "facebook": "",
    "rss": "",
    "phone": "(731) 635-9711",
    "email": "tt.mcdaniel@tn.gov",
    "address": "500 Highway 51 S\nRipley, TN 38063-4583"
  },
  {
    "id": "52",
    "name": "Lawrence County Health Department",
    "website": "http://www.lawrencecountytn.gov/government/departments/health-department",
    "twitter": "",
    "facebook": "",
    "rss": "",
    "phone": "(931) 762-9406",
    "email": "vin.Toms@tn.gov",
    "address": "2379 Buffalo Rd\nLawrenceburg, TN 38464-4810"
  },
  {
    "id": "53",
    "name": "Lewis County Health District",
    "website": "",
    "twitter": "",
    "facebook": "",
    "rss": "",
    "phone": "(931) 796-2204",
    "email": "rah.Russell@tn.gov",
    "address": "51 Smith Ave\nHohenwald, TN 38462-1124"
  },
  {
    "id": "54",
    "name": "Lincoln County Health Department",
    "website": "",
    "twitter": "",
    "facebook": "",
    "rss": "",
    "phone": "(931) 433-3231",
    "email": "bbie.Broadway@state.tn.us",
    "address": "1000 Washington St W Ste A\nFayetteville, TN 37334-2872"
  },
  {
    "id": "55",
    "name": "Loudon County Health Department",
    "website": "",
    "twitter": "",
    "facebook": "",
    "rss": "",
    "phone": "(865) 458-2514",
    "email": "resa.Harrill@state.tn.us",
    "address": "PO BOX 278\nLoudon, TN 37774-0278"
  },
  {
    "id": "56",
    "name": "Macon County Health Department",
    "website": "",
    "twitter": "",
    "facebook": "",
    "rss": "",
    "phone": "(615) 666-2142",
    "email": "sh.gipson@tn.gov",
    "address": "601 Highway 52 Byp E\nLafayette, TN 37083-1009"
  },
  {
    "id": "57",
    "name": "Marion County Health Department",
    "website": "",
    "twitter": "",
    "facebook": "",
    "rss": "",
    "phone": "(423) 942-2238",
    "email": "ssica.hill@tn.gov",
    "address": "24 E 7Th St\nJasper, TN 37347-3301"
  },
  {
    "id": "58",
    "name": "Marshall County Health Department",
    "website": "",
    "twitter": "",
    "facebook": "",
    "rss": "",
    "phone": "(931) 359-1551",
    "email": "gie.faulkner@tn.gov",
    "address": "206 Legion Ave\nLewisburg, TN 37091-2898"
  },
  {
    "id": "59",
    "name": "Maury County Health Department",
    "website": "",
    "twitter": "",
    "facebook": "",
    "rss": "",
    "phone": "(931) 560-1120",
    "email": "drew.kenney@tn.gov",
    "address": "1909 Hampshire Pike\nColumbia, TN 38401-5650"
  },
  {
    "id": "60",
    "name": "McMinn County Health Department",
    "website": "",
    "twitter": "",
    "facebook": "",
    "rss": "",
    "phone": "(423) 745-7431",
    "email": "annie.bentley@tn.gov",
    "address": "PO BOX 665\nAthens, TN 37371-0665"
  },
  {
    "id": "61",
    "name": "McNairy County Health Department",
    "website": "",
    "twitter": "",
    "facebook": "",
    "rss": "",
    "phone": "(731) 645-3474",
    "email": "ttie.kiddy@tn.gov",
    "address": "725 E Poplar Ave\nSelmer, TN 38375-1800"
  },
  {
    "id": "62",
    "name": "Meigs County Health Department",
    "website": "",
    "twitter": "",
    "facebook": "",
    "rss": "",
    "phone": "(423) 334-5185",
    "email": "cki.carr@tn.gov",
    "address": "PO BOX 157\nDecatur, TN 37322-0157"
  },
  {
    "id": "63",
    "name": "Metro Public Health Department",
    "website": "http://www.nashville.gov/Health-Department.aspx",
    "twitter": "https://twitter.com/NashvilleHealth",
    "facebook": "",
    "rss": "",
    "phone": "(615) 340-5622",
    "email": "nmi.areola@nashville.gov",
    "address": "2500 Charlotte Ave\nNashville, TN 37209-4129"
  },
  {
    "id": "64",
    "name": "Mid-Cumberland Region, Tennessee Department of Health",
    "website": "",
    "twitter": "",
    "facebook": "",
    "rss": "",
    "phone": "(615) 650-7030",
    "email": "njana.Stamm@tn.gov",
    "address": "710 Hart Ln\nNashville, TN 37243-1405"
  },
  {
    "id": "65",
    "name": "Monroe County Health Department",
    "website": "",
    "twitter": "",
    "facebook": "",
    "rss": "",
    "phone": "(423) 442-3993",
    "email": "resa.Harrill@tn.us",
    "address": "3469 New Highway 68\nMadisonville, TN 37354-5148"
  },
  {
    "id": "66",
    "name": "Montgomery County Health Department",
    "website": "",
    "twitter": "",
    "facebook": "",
    "rss": "",
    "phone": "931 648-5747",
    "email": "newell@mcgtn.net",
    "address": "330 Pageant LN\nClarksville, TN 37040-3854"
  },
  {
    "id": "67",
    "name": "Montgomery County Health Department",
    "website": "",
    "twitter": "",
    "facebook": "",
    "rss": "",
    "phone": "(931) 648-7210",
    "email": "ey.smith@tn.gov",
    "address": "330 Pageant Ln\nClarksville, TN 37040-3854"
  },
  {
    "id": "68",
    "name": "Moore County Health Department",
    "website": "",
    "twitter": "",
    "facebook": "",
    "rss": "",
    "phone": "(931) 759-4251",
    "email": "bbie.dickie@tn.gov",
    "address": "PO BOX 196\nLynchburg, TN 37352-0196"
  },
  {
    "id": "69",
    "name": "Morgan County Health Department",
    "website": "",
    "twitter": "",
    "facebook": "",
    "rss": "",
    "phone": "(423) 346-6272",
    "email": "ura.Conner@tn.gov",
    "address": "PO Box 343\nWartburg, TN 37887-0343"
  },
  {
    "id": "70",
    "name": "Northeast Region, Tennessee Department of Health",
    "website": "https://www.tn.gov/health",
    "twitter": "",
    "facebook": "",
    "rss": "",
    "phone": "(423) 979-4624",
    "email": "bekah.english@tn.gov",
    "address": "1233 Southwest Ave\nJohnson City, TN 37604-6596"
  },
  {
    "id": "71",
    "name": "Obion County Health Department",
    "website": "",
    "twitter": "",
    "facebook": "",
    "rss": "",
    "phone": "(731) 885-8722",
    "email": "m.James@tn.gov",
    "address": "PO Box 248\nUnion City, TN 38281-0248"
  },
  {
    "id": "72",
    "name": "Overton County Health Department",
    "website": "http://www.overtoncountytn.com/index.php?option=com_content&task=view&id=32&Itemid=104",
    "twitter": "",
    "facebook": "",
    "rss": "",
    "phone": "(931) 823-6260",
    "email": "dy.langford@tn.gov",
    "address": "5880 Bradford Hicks Dr\nLivingston, TN 38570-2236"
  },
  {
    "id": "73",
    "name": "Perry County Health Department",
    "website": "",
    "twitter": "",
    "facebook": "",
    "rss": "",
    "phone": "(931) 589-2138",
    "email": "rah.russell@tn.gov",
    "address": "31 Medical Dr\nLinden, TN 37096-3326"
  },
  {
    "id": "74",
    "name": "Pickett County Health Department",
    "website": "",
    "twitter": "",
    "facebook": "",
    "rss": "",
    "phone": "(931) 864-3178",
    "email": "dy.langford@tn.gov",
    "address": "1013 Woodlawn Dr\nByrdstown, TN 38549-2317"
  },
  {
    "id": "75",
    "name": "Polk County Department of Health",
    "website": "",
    "twitter": "",
    "facebook": "",
    "rss": "",
    "phone": "423-3384533",
    "email": "annie.bentley@tn.gov",
    "address": "2279 Parksville RD\nBenton, TN 37307-3803"
  },
  {
    "id": "76",
    "name": "Polk-Benton County Health Department",
    "website": "http://www.polkgovernment.com/health-dept.php",
    "twitter": "",
    "facebook": "",
    "rss": "",
    "phone": "(423) 338-4533",
    "email": "annie.bentley@tn.gov",
    "address": "2279 Parksville Rd\nBenton, TN 37307-3803"
  },
  {
    "id": "77",
    "name": "Polk-Copper Basin",
    "website": "",
    "twitter": "",
    "facebook": "",
    "rss": "",
    "phone": "(423) 338-4533 (108)",
    "email": "",
    "address": "840 Cherokee Trl\nCopperhill, TN 37317-5220"
  },
  {
    "id": "78",
    "name": "Putnam County Health Department",
    "website": "",
    "twitter": "",
    "facebook": "",
    "rss": "",
    "phone": "(931) 528-2531",
    "email": "sa.Bumbalough@tn.gov",
    "address": "701 County Services Dr\nCookeville, TN 38501-4338"
  },
  {
    "id": "79",
    "name": "Rhea County Health Department",
    "website": "",
    "twitter": "",
    "facebook": "",
    "rss": "",
    "phone": "(423) 775-7819",
    "email": "cki.carr@tn.gov",
    "address": "344 Eagle Ln\nEvensville, TN 37332-3200"
  },
  {
    "id": "80",
    "name": "Roane County Health Department",
    "website": "",
    "twitter": "",
    "facebook": "",
    "rss": "",
    "phone": "(865) 354-1220",
    "email": "ura.Conner@tn.gov",
    "address": "1362 N Gateway Ave\nRockwood, TN 37854-4108"
  },
  {
    "id": "81",
    "name": "Robertson County Dental Department",
    "website": "",
    "twitter": "",
    "facebook": "",
    "rss": "",
    "phone": "615-384-0208",
    "email": "nessa.Watkins@tn.gov",
    "address": "806 S Brown ST\nSpringfield, TN 37172-2920"
  },
  {
    "id": "82",
    "name": "Robertson County Health Department",
    "website": "",
    "twitter": "",
    "facebook": "",
    "rss": "",
    "phone": "(615) 384-0208",
    "email": "onda.hall@tn.gov",
    "address": "800 S Brown St\nSpringfield, TN 37172-2920"
  },
  {
    "id": "83",
    "name": "Rutherford County Health Department",
    "website": "",
    "twitter": "",
    "facebook": "",
    "rss": "",
    "phone": "(615) 898-7785",
    "email": "na.garrett@tn.gov",
    "address": "100 W Burton St\nMurfreesboro, TN 37130-3657"
  },
  {
    "id": "84",
    "name": "Scott County Health Department",
    "website": "",
    "twitter": "",
    "facebook": "",
    "rss": "",
    "phone": "(423) 663-2445",
    "email": "t.miller@tn.gov",
    "address": "PO BOX 88\nHuntsville, TN 37756-0088"
  },
  {
    "id": "85",
    "name": "Sequatchie County Health Department",
    "website": "",
    "twitter": "",
    "facebook": "",
    "rss": "",
    "phone": "(423) 949-3619",
    "email": "arlene.nunley@tn.gov",
    "address": "16939 Rankin Ave\nDunlap, TN 37327-7029"
  },
  {
    "id": "86",
    "name": "Sevier County Health Department",
    "website": "",
    "twitter": "",
    "facebook": "",
    "rss": "",
    "phone": "(865) 637-8733",
    "email": "na.Chambers@state.tn.us",
    "address": "PO BOX 4648\nSevierville, TN 37864-4648"
  },
  {
    "id": "87",
    "name": "Shelby County Health Department",
    "website": "http://www.shelbytnhealth.com/",
    "twitter": "",
    "facebook": "",
    "rss": "",
    "phone": "(901) 222-9080",
    "email": "isa.haushalter@shelbycountytn.gov",
    "address": "814 Jefferson Ave\nMemphis, TN 38105-5041"
  },
  {
    "id": "88",
    "name": "Smith County Health Department",
    "website": "",
    "twitter": "",
    "facebook": "",
    "rss": "",
    "phone": "(615) 735-0242",
    "email": "ances.Reece@state.tn.us",
    "address": "251 Joy Alford Way\nCarthage, TN 37030-3047"
  },
  {
    "id": "89",
    "name": "South Central Region, Tennessee Department of Health",
    "website": "",
    "twitter": "",
    "facebook": "",
    "rss": "",
    "phone": "(931) 490-8337 (128)",
    "email": "i.mitchell@tn.gov",
    "address": "1216 Trotwood Ave\nColumbia, TN 38401-6406"
  },
  {
    "id": "90",
    "name": "Southeast Region, Tennessee Department of Health",
    "website": "",
    "twitter": "",
    "facebook": "",
    "rss": "",
    "phone": "(423) 634-5891",
    "email": "enn.czarnecki@tn.gov",
    "address": "540 Mccallie Ave Ste 450\nChattanooga, TN 37402-2033"
  },
  {
    "id": "91",
    "name": "Stewart County Health Department",
    "website": "",
    "twitter": "",
    "facebook": "",
    "rss": "",
    "phone": "(931) 232-5329",
    "email": "ren.anderson@tn.gov",
    "address": "PO BOX 497\nDover, TN 37058-0497"
  },
  {
    "id": "92",
    "name": "Sullivan County Regional Health Department",
    "website": "http://www.sullivanhealth.org",
    "twitter": "",
    "facebook": "",
    "rss": "",
    "phone": "(423) 279-2792",
    "email": "ayes@sullivanhealth.org",
    "address": "PO BOX 630\nBlountville, TN 37617-0630"
  },
  {
    "id": "93",
    "name": "Sumner County Health Department",
    "website": "",
    "twitter": "",
    "facebook": "",
    "rss": "",
    "phone": "(615) 206-1100",
    "email": "l.hendricks@tn.gov",
    "address": "1005 Union School Rd\nGallatin, TN 37066-2084"
  },
  {
    "id": "94",
    "name": "Tipton County Health Department",
    "website": "",
    "twitter": "",
    "facebook": "",
    "rss": "",
    "phone": "(901) 476-0235",
    "email": "tt.mcdaniel@tn.gov",
    "address": "PO BOX 685\nCovington, TN 38019-0685"
  },
  {
    "id": "95",
    "name": "Trousdale County Health Department",
    "website": "",
    "twitter": "",
    "facebook": "",
    "rss": "",
    "phone": "(615) 374-2112",
    "email": "m.diffenderfer@tn.gov",
    "address": "541 E Main St\nHartsville, TN 37074-1220"
  },
  {
    "id": "96",
    "name": "Unicoi County Health Department",
    "website": "",
    "twitter": "",
    "facebook": "",
    "rss": "",
    "phone": "(423) 743-9103",
    "email": "ndy.sailor@tn.gov",
    "address": "101 Okolona Dr\nErwin, TN 37650-1387"
  },
  {
    "id": "97",
    "name": "Union County Health Department",
    "website": "",
    "twitter": "",
    "facebook": "",
    "rss": "",
    "phone": "(865) 992-3867",
    "email": "arles.H.Turner@tn.gov",
    "address": "PO BOX 460\nMaynardville, TN 37807-0460"
  },
  {
    "id": "98",
    "name": "Upper Cumberland Region, Tennessee Department of Health",
    "website": "https://www.tn.gov/health/health-program-areas/oralhealth/clinics/upper-cumberland-region.html",
    "twitter": "",
    "facebook": "",
    "rss": "",
    "phone": "(931) 528-7531",
    "email": "bbie.johnson@tn.gov",
    "address": "1100 England Dr\nCookeville, TN 38501-0924"
  },
  {
    "id": "99",
    "name": "Van Buren County Health Department",
    "website": "",
    "twitter": "",
    "facebook": "",
    "rss": "",
    "phone": "(931) 946-2643",
    "email": "ndy.doyle@tn.gov",
    "address": "907 Old Mcminnville St\nSpencer, TN 38585-3200"
  },
  {
    "id": "100",
    "name": "Warren County Health Department",
    "website": "",
    "twitter": "",
    "facebook": "",
    "rss": "",
    "phone": "(931) 473-8468",
    "email": "chael.railling@tn.gov",
    "address": "1401 Sparta St\nMcminnville, TN 37110-1301"
  },
  {
    "id": "101",
    "name": "Washington County Health Department",
    "website": "",
    "twitter": "",
    "facebook": "",
    "rss": "",
    "phone": "(423) 975-7327",
    "email": "risten.minnick@tn.gov",
    "address": "219 Princeton Rd\nJohnson City, TN 37601-2052"
  },
  {
    "id": "102",
    "name": "Wayne County Health Department",
    "website": "",
    "twitter": "",
    "facebook": "",
    "rss": "",
    "phone": "(931) 722-3292",
    "email": "vin.Toms@tn.gov",
    "address": "725 S Main ST\nWaynesboro, TN 38485-2638"
  },
  {
    "id": "103",
    "name": "Weakley County Health Department",
    "website": "",
    "twitter": "",
    "facebook": "",
    "rss": "",
    "phone": "(731) 364-2258",
    "email": "m.James@state.tn.us",
    "address": "9852 Highway 22\nDresden, TN 38225-1804"
  },
  {
    "id": "104",
    "name": "West Region, Tennessee Department of Health",
    "website": "",
    "twitter": "",
    "facebook": "",
    "rss": "",
    "phone": "(731) 421-6701",
    "email": "rilyn.Barnes@tn.gov",
    "address": "295 Summar Street\nJackson, TN 38301-3905"
  },
  {
    "id": "105",
    "name": "White County Health Department",
    "website": "",
    "twitter": "",
    "facebook": "",
    "rss": "",
    "phone": "(931) 836-2201",
    "email": "drea.fox@tn.gov",
    "address": "135 Walker St\nSparta, TN 38583-1725"
  },
  {
    "id": "106",
    "name": "Williamson County Health Department",
    "website": "",
    "twitter": "",
    "facebook": "",
    "rss": "",
    "phone": "(615) 794-1258",
    "email": "therine.montgomery@tn.gov",
    "address": "1324 W Main St\nFranklin, TN 37064-3784"
  },
  {
    "id": "107",
    "name": "Wilson County Health Department",
    "website": "",
    "twitter": "",
    "facebook": "",
    "rss": "",
    "phone": "(615) 444-5325",
    "email": "m.diffenderfer@tn.gov",
    "address": "927 E Baddour Pkwy\nLebanon, TN 37087-3706"
  }
]